openptv_python/__init__.py
openptv_python/calibration.py
openptv_python/constants.py
openptv_python/correspondences.py
openptv_python/epi.py
openptv_python/find_candidate.py
openptv_python/image_processing.py
openptv_python/imgcoord.py
openptv_python/lsqadj.py
openptv_python/multimed.py
openptv_python/orientation.py
openptv_python/parameters.py
openptv_python/ptv.py.bck
openptv_python/ray_tracing.py
openptv_python/segmentation.py
openptv_python/sortgrid.py
openptv_python/track.py
openptv_python/tracking_frame_buf.py
openptv_python/tracking_frame_buf_header.txt
openptv_python/tracking_run.py
openptv_python/trafo.py
openptv_python/vec_utils.py
openptv_python/version.py
openptv_python-0.0.1.dist-info/LICENSE
openptv_python-0.0.1.dist-info/METADATA
openptv_python-0.0.1.dist-info/WHEEL
openptv_python-0.0.1.dist-info/top_level.txt
openptv_python-0.0.1.dist-info/RECORD
